chuxel/__init__.py
chuxel/chuxel.py
chuxel-0.0.1.dist-info/LICENSE
chuxel-0.0.1.dist-info/METADATA
chuxel-0.0.1.dist-info/WHEEL
chuxel-0.0.1.dist-info/top_level.txt
chuxel-0.0.1.dist-info/RECORD
