Metadata-Version: 2.1
Name: chuxel
Version: 0.0.1
Summary: chuxel
Home-page: UNKNOWN
Author: hckmtrx
Author-email: <hckmtrx@gmail.com>
License: UNKNOWN
Keywords: python,chuxel
Platform: UNKNOWN
Classifier: Development Status :: 1 - Planning
Classifier: Intended Audience :: Developers
Classifier: Programming Language :: Python :: 3
Classifier: Operating System :: Unix
Classifier: Operating System :: MacOS :: MacOS X
Classifier: Operating System :: Microsoft :: Windows
License-File: LICENSE
